{
    "version": "0.4.0",
    "homepage": "https://trygloo.com",
    "url": "https://github.com/GlooHQ/baml/releases/download/releases%2Fbaml-cli%2Fv0.4.0/baml.exe",
    "bin": "baml.exe",
    "hash": "a1daebd0f0eec7383c6d0c01a8adee94a2190622f39cd14b2b61871b1bedc468",
    "checkver": "github",
    "autoupdate": {
        "architecture": {
            "64bit": {
                "url": "https://github.com/GlooHQ/baml/releases/download/releases%2Fbaml-cli%2Fv0.4.0/baml.exe"
            }
        }
    }
}